datav_server/IdUtil.py
datav_server/__init__.py
datav_server/bas_dic_util.py
datav_server/common_db.py
datav_server/datav_common_util.py
datav_server/db_factory.py
datav_server/mysql_db.py
datav_server/sqlite3_db.py
datav_server-1.0.6.dist-info/LICENSE
datav_server-1.0.6.dist-info/METADATA
datav_server-1.0.6.dist-info/WHEEL
datav_server-1.0.6.dist-info/top_level.txt
datav_server-1.0.6.dist-info/RECORD
