Metadata-Version: 2.1
Name: datav-server
Version: 1.0.6
Summary: datav爬取数据通用组件服务端
Home-page: UNKNOWN
Author: python之父·博思之光·杨瑞
License: UNKNOWN
Platform: UNKNOWN
License-File: LICENSE
Requires-Dist: sqlparse
Requires-Dist: PyMySQL (==1.0.2)
